{"trial_id": "009", "hyperparameters": {"space": [{"class_name": "Int", "config": {"name": "conv_1_filter", "default": null, "conditions": [], "min_value": 32, "max_value": 512, "step": 32, "sampling": "linear"}}, {"class_name": "Choice", "config": {"name": "conv_1_kernel", "default": 3, "conditions": [], "values": [3, 5], "ordered": true}}, {"class_name": "Int", "config": {"name": "conv_2_filter", "default": null, "conditions": [], "min_value": 32, "max_value": 64, "step": 16, "sampling": "linear"}}, {"class_name": "Choice", "config": {"name": "conv_2_kernel", "default": 3, "conditions": [], "values": [3, 5], "ordered": true}}, {"class_name": "Int", "config": {"name": "units", "default": null, "conditions": [], "min_value": 32, "max_value": 512, "step": 32, "sampling": "linear"}}, {"class_name": "Choice", "config": {"name": "learning_rate", "default": 0.01, "conditions": [], "values": [0.01, 0.001, 0.0001], "ordered": true}}], "values": {"conv_1_filter": 192, "conv_1_kernel": 3, "conv_2_filter": 48, "conv_2_kernel": 3, "units": 96, "learning_rate": 0.001}}, "metrics": {"metrics": {"loss": {"direction": "min", "observations": [{"value": [0.0014073034981265664], "step": 33}]}, "accuracy": {"direction": "max", "observations": [{"value": [0.9996825456619263], "step": 33}]}, "val_loss": {"direction": "min", "observations": [{"value": [1.0518553256988525], "step": 33}]}, "val_accuracy": {"direction": "max", "observations": [{"value": [0.9011428356170654], "step": 33}]}}}, "score": 0.9011428356170654, "best_step": 33, "status": "COMPLETED", "message": null}